core/MAU.v
module MAU (
    input clk,
    input ctrl_mem_read,
    input ctrl_mem_write,
    input [31:0] address,
    input [31:0] write_data,
    output reg [31:0] read_data,
    output reg stat_mem_read_done,
    output reg stat_mem_write_done
);

reg [31:0] memory [0:255]; // Example memory array

always @(posedge clk) begin
    if (ctrl_mem_read) begin
        read_data <= memory[address[7:0]];
        stat_mem_read_done <= 1'b1;
        $display("Time: %0t | MAU: Read Data %h from Address %h", $time, read_data, address);
    end else begin
        stat_mem_read_done <= 1'b0;
    end

    if (ctrl_mem_write) begin
        memory[address[7:0]] <= write_data;
        stat_mem_write_done <= 1'b1;
        $display("Time: %0t | MAU: Write Data %h to Address %h", $time, write_data, address);
    end else begin
        stat_mem_write_done <= 1'b0;
    end
end

endmodule

core/ALU.v
module ALU (
    input clk,
    input reset,
    input ctrl_alu_op_enable,  // Control signal to start ALU operation
    input [31:0] operand1,
    input [31:0] operand2,
    input [3:0] alu_control,    // ALU control signals
    output reg [31:0] result,   // ALU result
    output reg stat_execution_done, // Status signal to indicate ALU operation completion
    output reg zero_flag        // Zero flag for branch decisions
);

always @(posedge clk or posedge reset) begin
    if (reset) begin
        stat_execution_done <= 1'b0;
        result <= 32'b0;
        zero_flag <= 1'b0;
    end else if (ctrl_alu_op_enable) begin
        case (alu_control)
            4'b0000: result <= operand1 + operand2;  // ADD operation
            4'b0001: result <= operand1 - operand2;  // SUB operation
            4'b0010: result <= operand1 & operand2;  // AND operation
            4'b0011: result <= operand1 | operand2;  // OR operation
            // Add more ALU operations as needed
            default: result <= 32'b0;
        endcase

        zero_flag <= (result == 32'b0);  // Set zero flag if result is zero
        stat_execution_done <= 1'b1;     // Indicate ALU operation done

        $display("ALU Operation: Operand1=%h | Operand2=%h | Result=%h | ZeroFlag=%b", operand1, operand2, result, zero_flag);
    end
end

endmodule

core/RF.v
module RF (
    input clk,
    input ctrl_reg_write_enable,
    input [4:0] read_reg1,
    input [4:0] read_reg2,
    input [4:0] write_reg,
    input [31:0] write_data,
    output reg [31:0] read_data1,
    output reg [31:0] read_data2,
    output reg stat_reg_write_done
);

reg [31:0] registers [0:31];

always @(posedge clk) begin
    read_data1 <= registers[read_reg1];
    read_data2 <= registers[read_reg2];
    
    if (ctrl_reg_write_enable) begin
        registers[write_reg] <= write_data;
        stat_reg_write_done <= 1'b1;
        $display("Time: %0t | RF: Write Data %h to Register %h", $time, write_data, write_reg);
    end else begin
        stat_reg_write_done <= 1'b0;
    end
end

endmodule

core/IDU.v
module IDU (
    input clk,
    input reset,
    input ctrl_decode_enable,
    input [31:0] instruction,
    output reg stat_instruction_decoded,
    output reg [4:0] rd,
    output reg [4:0] rs1,
    output reg [4:0] rs2,
    output reg [31:0] immediate,
    output reg is_r_type,
    output reg is_i_type,
    output reg is_load,
    output reg is_store,
    output reg is_branch,
    output reg is_jump,
    output reg [3:0] alu_control
);

always @(posedge clk or posedge reset) begin
    if (reset) begin
        stat_instruction_decoded <= 1'b0;
    end else if (ctrl_decode_enable) begin
        // Example decoding logic
        rs1 <= instruction[19:15];
        rs2 <= instruction[24:20];
        rd <= instruction[11:7];
        immediate <= instruction[31:20];
        is_r_type <= (instruction[6:0] == 7'b0110011);
        is_i_type <= (instruction[6:0] == 7'b0010011);
        is_load <= (instruction[6:0] == 7'b0000011);
        is_store <= (instruction[6:0] == 7'b0100011);
        is_branch <= (instruction[6:0] == 7'b1100011);
        is_jump <= (instruction[6:0] == 7'b1101111);
        alu_control <= 4'b0010; // Example control
        stat_instruction_decoded <= 1'b1;
        $display("Time: %0t | IDU: Decoded Instruction -> rd: %h, rs1: %h, rs2: %h, immediate: %h", $time, rd, rs1, rs2, immediate);
    end else begin
        stat_instruction_decoded <= 1'b0;
    end
end

endmodule

core/IFU.v
module IFU (
    input wire clk,
    input wire reset,
    input wire ctr_mem_read_enable,
    input wire [31:0] pc,  // Program counter input
    output reg [31:0] instruction,  // 32-bit instruction output
    output reg stat_instruction_fetched
);
    // Instruction memory or fetching logic here

    always @(posedge clk or posedge reset) begin
        if (reset) begin
            instruction <= 32'b0;
            stat_instruction_fetched <= 1'b0;
        end else if (ctr_mem_read_enable) begin
            // Example: Fetch instruction from memory based on the PC
            // instruction <= memory[pc];
            stat_instruction_fetched <= 1'b1;
        end
    end
endmodule

PC.v
module PC (
    input clk,
    input reset,
    input pc_write_enable,
    input [31:0] pc_next,
    output reg [31:0] pc
);

always @(posedge clk or posedge reset) begin
    if (reset) begin
        pc <= 32'b0;
    end else if (pc_write_enable) begin
        pc <= pc_next;
    end
end

endmodule

riscv_core.v
module riscv_core (
    input clk,
    input reset
);

// State enumeration
parameter WAIT = 3'b000;
parameter FETCH = 3'b001;
parameter DECODE = 3'b010;
parameter EXECUTE = 3'b011;
parameter READ_MEMORY = 3'b100;
parameter WRITE_MEMORY = 3'b101;
parameter READ_REGISTER = 3'b110;
parameter WRITE_REGISTER = 3'b111;

reg [2:0] current_state, next_state;
reg [3:0] wait_count;

// Internal signals
wire [31:0] pc, next_pc, instruction, immediate, alu_result, read_data, write_data;
wire [3:0] alu_control;
wire zero_flag;
wire [4:0] rd, rs1, rs2;

// Control signals decoded from the instruction (as wires)
wire is_r_type;
wire is_i_type;
wire is_load;
wire is_store;
wire is_branch;
wire is_jump;

// Internal control signals for state machine (as regs)
reg ctrl_instruction_mem_read_enable;
reg ctrl_decode_enable;
reg ctrl_alu_op_enable;
reg ctrl_mem_read_enable;
reg ctrl_mem_write_enable;
reg ctrl_reg_write_enable;
reg ctrl_pc_update_enable;
reg ctrl_branch_enable;
reg ctrl_jump_enable;

// Status signals (declared as wire)
wire stat_instruction_fetched, stat_instruction_decoded, stat_reg_write_done, stat_mem_read_done, stat_mem_write_done, stat_execution_done;

// Instantiate the Program Counter
PC pc_inst (
    .clk(clk),
    .reset(reset),
    .pc_write_enable(ctrl_pc_update_enable),
    .pc_next(next_pc),
    .pc(pc)
);

// Instantiate the Instruction Fetch Unit
IFU ifu_inst (
    .clk(clk),
    .reset(reset),
    .ctr_mem_read_enable(ctrl_instruction_mem_read_enable),
    .pc(pc),
    .instruction(instruction),
    .stat_instruction_fetched(stat_instruction_fetched)
);

// Instantiate the Instruction Decode Unit
IDU idu_inst (
    .clk(clk),
    .reset(reset),
    .ctrl_decode_enable(ctrl_decode_enable),
    .instruction(instruction),
    .stat_instruction_decoded(stat_instruction_decoded),
    .rd(rd),
    .rs1(rs1),
    .rs2(rs2),
    .immediate(immediate),
    .is_r_type(is_r_type),
    .is_i_type(is_i_type),
    .is_load(is_load),
    .is_store(is_store),
    .is_branch(is_branch),
    .is_jump(is_jump),
    .alu_control(alu_control)
);

// Instantiate the Register File
RF rf_inst (
    .clk(clk),
    .ctrl_reg_write_enable(ctrl_reg_write_enable),
    .read_reg1(rs1),
    .read_reg2(rs2),
    .write_reg(rd),
    .write_data(write_data),
    .read_data1(read_data),
    .read_data2(immediate),
    .stat_reg_write_done(stat_reg_write_done)
);

// Instantiate the ALU
ALU alu_inst (
    .clk(clk),
    .reset(reset),
    .operand1(read_data),
    .ctrl_alu_op_enable(ctrl_alu_op_enable),
    .operand2(ctrl_alu_op_enable ? immediate : read_data),
    .alu_control(alu_control),
    .result(alu_result),
    .stat_execution_done(stat_execution_done),
    .zero_flag(zero_flag)
);

// Instantiate the Memory Access Unit
MAU mau_inst (
    .clk(clk),
    .ctrl_mem_read(ctrl_mem_read_enable),
    .ctrl_mem_write(ctrl_mem_write_enable),
    .address(alu_result),
    .write_data(read_data),
    .read_data(write_data),
    .stat_mem_read_done(stat_mem_read_done),
    .stat_mem_write_done(stat_mem_write_done)
);

// State Machine Logic
always @(posedge clk or posedge reset) begin
    if (reset) begin
        current_state <= WAIT;
        wait_count <= 4'b0;

        // Reset all control signals
        ctrl_instruction_mem_read_enable <= 1'b0;
        ctrl_decode_enable <= 1'b0;
        ctrl_alu_op_enable <= 1'b0;
        ctrl_mem_read_enable <= 1'b0;
        ctrl_mem_write_enable <= 1'b0;
        ctrl_reg_write_enable <= 1'b0;
        ctrl_pc_update_enable <= 1'b0;
        ctrl_branch_enable <= 1'b0;
        ctrl_jump_enable <= 1'b0;
    end else begin
        current_state <= next_state;
    end

    // Display current state information
    $display("Time: %0t | State: %b | PC: %h | Instruction: %h", $time, current_state, pc, instruction);
end

// Next State Logic and Control Signal Assertion
always @(posedge clk) begin
    // Default de-assertion of internal control signals
    ctrl_instruction_mem_read_enable <= 1'b0;
    ctrl_decode_enable <= 1'b0;
    ctrl_alu_op_enable <= 1'b0;
    ctrl_mem_read_enable <= 1'b0;
    ctrl_mem_write_enable <= 1'b0;
    ctrl_reg_write_enable <= 1'b0;
    ctrl_pc_update_enable <= 1'b0;
    ctrl_branch_enable <= 1'b0;
    ctrl_jump_enable <= 1'b0;

    case (current_state)
        WAIT: begin
            if (wait_count < 2) begin  // Stay in WAIT state for 2 cycles
                wait_count <= wait_count + 1;
                next_state <= WAIT;
            end else begin
                next_state <= FETCH;
                wait_count <= 4'b0;
            end
        end
        FETCH: begin
            ctrl_instruction_mem_read_enable <= 1'b1;
            if (stat_instruction_fetched) begin
                next_state <= DECODE;
            end else begin
                next_state <= FETCH; // Remain in FETCH if not done
            end
        end
        DECODE: begin
            ctrl_decode_enable <= 1'b1;
            if (stat_instruction_decoded) begin
                next_state <= READ_REGISTER;
            end else begin
                next_state <= DECODE; // Remain in DECODE if not done
            end
        end
        READ_REGISTER: begin
            next_state <= EXECUTE;
        end
        EXECUTE: begin
            if (is_r_type || is_i_type) begin
                ctrl_alu_op_enable <= 1'b1;
                if (stat_execution_done) begin
                    ctrl_alu_op_enable <= 1'b0;
                    next_state <= WRITE_REGISTER;
                end else begin
                    next_state <= EXECUTE; // Remain in EXECUTE if not done
                end
            end else if (is_branch) begin
                ctrl_branch_enable <= 1'b1;
                next_state <= WAIT; 
            end else if (is_jump) begin
                ctrl_jump_enable <= 1'b1;
                next_state <= WRITE_REGISTER;
            end else begin
                next_state <= EXECUTE; // Remain in EXECUTE if not done
            end
        end
        READ_MEMORY: begin
            ctrl_mem_read_enable <= 1'b1;
            if (stat_mem_read_done) begin
                next_state <= WRITE_REGISTER;
            end else begin
                next_state <= READ_MEMORY; // Remain in READ_MEMORY if not done
            end
        end
        WRITE_MEMORY: begin
            ctrl_mem_write_enable <= 1'b1;
            if (stat_mem_write_done) begin
                next_state <= WAIT;
            end else begin
                next_state <= WRITE_MEMORY; // Remain in WRITE_MEMORY if not done
            end
        end
        WRITE_REGISTER: begin
            ctrl_reg_write_enable <= 1'b1;
            if (stat_reg_write_done) begin
                next_state <= WAIT;
            end else begin
                next_state <= WRITE_REGISTER; // Remain in WRITE_REGISTER if not done
            end
        end
    endcase
end

endmodule

core/riscv_core_tb.v
module tb_riscv_core;
    reg clk;
    reg reset;

    riscv_core uut (
        .clk(clk),
        .reset(reset)
    );

    initial begin
        $dumpfile("riscv_core_tb.vcd");
        $dumpvars(0, tb_riscv_core);
        clk = 0;
        reset = 1;
        #5 reset = 0;

        // Wait for the core to go through the states
        #500 $finish;
    end

    always #5 clk = ~clk;

    // Monitor the state and PC
    initial begin
        $monitor("Time: %0t | PC: %h | State: %b | Instruction: %h", $time, uut.pc, uut.current_state, uut.ifu_inst.instruction);
    end
endmodule

core/riscv_core_tb.vcd
$date
	Sat Aug 10 11:08:40 2024
$end
$version
	Icarus Verilog
$end
$timescale
	1s
$end
$scope module tb_riscv_core $end
$var reg 1 ! clk $end
$var reg 1 " reset $end
$scope module uut $end
$var wire 1 ! clk $end
$var wire 32 # immediate [31:0] $end
$var wire 32 $ next_pc [31:0] $end
$var wire 1 " reset $end
$var wire 1 % zero_flag $end
$var wire 32 & write_data [31:0] $end
$var wire 1 ' stat_reg_write_done $end
$var wire 1 ( stat_mem_write_done $end
$var wire 1 ) stat_mem_read_done $end
$var wire 1 * stat_instruction_fetched $end
$var wire 1 + stat_instruction_decoded $end
$var wire 1 , stat_execution_done $end
$var wire 5 - rs2 [4:0] $end
$var wire 5 . rs1 [4:0] $end
$var wire 32 / read_data [31:0] $end
$var wire 5 0 rd [4:0] $end
$var wire 32 1 pc [31:0] $end
$var wire 1 2 is_store $end
$var wire 1 3 is_r_type $end
$var wire 1 4 is_load $end
$var wire 1 5 is_jump $end
$var wire 1 6 is_i_type $end
$var wire 1 7 is_branch $end
$var wire 32 8 instruction [31:0] $end
$var wire 32 9 alu_result [31:0] $end
$var wire 4 : alu_control [3:0] $end
$var reg 1 ; ctrl_alu_op_enable $end
$var reg 1 < ctrl_branch_enable $end
$var reg 1 = ctrl_decode_enable $end
$var reg 1 > ctrl_instruction_mem_read_enable $end
$var reg 1 ? ctrl_jump_enable $end
$var reg 1 @ ctrl_mem_read_enable $end
$var reg 1 A ctrl_mem_write_enable $end
$var reg 1 B ctrl_pc_update_enable $end
$var reg 1 C ctrl_reg_write_enable $end
$var reg 3 D current_state [2:0] $end
$var reg 3 E next_state [2:0] $end
$var reg 4 F wait_count [3:0] $end
$scope module alu_inst $end
$var wire 1 ! clk $end
$var wire 1 ; ctrl_alu_op_enable $end
$var wire 32 G operand2 [31:0] $end
$var wire 1 " reset $end
$var wire 32 H operand1 [31:0] $end
$var wire 4 I alu_control [3:0] $end
$var reg 32 J result [31:0] $end
$var reg 1 , stat_execution_done $end
$var reg 1 % zero_flag $end
$upscope $end
$scope module idu_inst $end
$var wire 1 ! clk $end
$var wire 1 = ctrl_decode_enable $end
$var wire 1 " reset $end
$var wire 32 K instruction [31:0] $end
$var reg 4 L alu_control [3:0] $end
$var reg 32 M immediate [31:0] $end
$var reg 1 7 is_branch $end
$var reg 1 6 is_i_type $end
$var reg 1 5 is_jump $end
$var reg 1 4 is_load $end
$var reg 1 3 is_r_type $end
$var reg 1 2 is_store $end
$var reg 5 N rd [4:0] $end
$var reg 5 O rs1 [4:0] $end
$var reg 5 P rs2 [4:0] $end
$var reg 1 + stat_instruction_decoded $end
$upscope $end
$scope module ifu_inst $end
$var wire 1 ! clk $end
$var wire 1 > ctr_mem_read_enable $end
$var wire 1 " reset $end
$var wire 32 Q pc [31:0] $end
$var reg 32 R instruction [31:0] $end
$var reg 1 * stat_instruction_fetched $end
$upscope $end
$scope module mau_inst $end
$var wire 32 S address [31:0] $end
$var wire 1 ! clk $end
$var wire 1 @ ctrl_mem_read $end
$var wire 1 A ctrl_mem_write $end
$var wire 32 T write_data [31:0] $end
$var reg 32 U read_data [31:0] $end
$var reg 1 ) stat_mem_read_done $end
$var reg 1 ( stat_mem_write_done $end
$upscope $end
$scope module pc_inst $end
$var wire 1 ! clk $end
$var wire 32 V pc_next [31:0] $end
$var wire 1 B pc_write_enable $end
$var wire 1 " reset $end
$var reg 32 W pc [31:0] $end
$upscope $end
$scope module rf_inst $end
$var wire 1 ! clk $end
$var wire 1 C ctrl_reg_write_enable $end
$var wire 5 X read_reg1 [4:0] $end
$var wire 5 Y read_reg2 [4:0] $end
$var wire 32 Z write_data [31:0] $end
$var wire 5 [ write_reg [4:0] $end
$var reg 32 \ read_data1 [31:0] $end
$var reg 32 ] read_data2 [31:0] $end
$var reg 1 ' stat_reg_write_done $end
$upscope $end
$upscope $end
$upscope $end
$enddefinitions $end
#0
$dumpvars
bx ]
bx \
bx [
bx Z
bx Y
bx X
b0 W
bz V
bx U
bx T
b0 S
b0 R
b0 Q
bx P
bx O
bx N
bx M
bx L
b0 K
b0 J
bx I
bx H
bx G
b0 F
bx E
b0 D
0C
0B
0A
0@
0?
0>
0=
0<
0;
bx :
b0 9
b0 8
x7
x6
x5
x4
x3
x2
b0 1
bx 0
bx /
bx .
bx -
0,
0+
0*
x)
x(
x'
bx &
0%
bz $
bx #
1"
0!
$end
#5
bx D
0'
0(
0)
b0 E
b1 F
1!
0"
#10
0!
#15
b0 D
1!
#20
0!
#25
b10 F
1!
#30
0!
#35
b0 F
b1 E
1!
#40
0!
#45
b1 D
b0 E
b1 F
1!
#50
0!
#55
b0 D
b1 E
1>
1!
#60
0!
#65
b1 D
1*
b0 E
b10 F
0>
1!
#70
0!
#75
b0 D
b10 E
1>
1!
#80
0!
#85
b10 D
b0 F
b1 E
0>
1!
#90
0!
#95
b1 D
b10 E
1=
1!
#100
0!
#105
b10 D
1+
b10 :
b10 I
b10 L
05
07
02
04
06
03
b0 M
b0 0
b0 N
b0 [
b0 -
b0 P
b0 Y
b0 .
b0 O
b0 X
1>
0=
1!
#110
0!
#115
0+
b110 E
1=
0>
1!
#120
0!
#125
b110 D
1+
b10 E
1=
1!
#130
0!
#135
b10 D
b11 E
0=
1!
#140
0!
#145
b11 D
0+
b110 E
1=
1!
#150
0!
#155
1+
b110 D
b11 E
0=
1!
#160
0!
#165
b11 D
0+
1!
